{"dist-tags":{"latest":"3.0.0","next":"2.0.0-rc.1"},"modified":"2023-07-31T11:02:32.230Z","name":"d3-brush","versions":{"3.0.0":{"name":"d3-brush","version":"3.0.0","dependencies":{"d3-dispatch":"1 - 3","d3-drag":"2 - 3","d3-interpolate":"1 - 3","d3-selection":"3","d3-transition":"3"},"devDependencies":{"eslint":"7","mocha":"9","rollup":"2","rollup-plugin-terser":"7"},"directories":{},"dist":{"shasum":"6f767c4ed8dcb79de7ede3e1c0f89e63ef64d31c","size":14219,"noattachment":false,"tarball":"https://registry.npmmirror.com/d3-brush/-/d3-brush-3.0.0.tgz","integrity":"sha512-ALnjWlVYkXsVIGlOsuWH1+3udkYFI48Ljihfnh8FZPF2QS9o+PzGLBslO0PjzVoHLZ2KCVgAM8NVkXPJB2aNnQ=="},"engines":{"node":">=12"},"_hasShrinkwrap":false,"_npmUser":{"name":"mbostock","email":"mike@ocks.org"}},"2.1.0":{"name":"d3-brush","version":"2.1.0","dependencies":{"d3-dispatch":"1 - 2","d3-drag":"2","d3-interpolate":"1 - 2","d3-selection":"2","d3-transition":"2"},"devDependencies":{"eslint":"6","rollup":"1","rollup-plugin-terser":"5","tape":"4"},"directories":{},"dist":{"shasum":"adadfbb104e8937af142e9a6e2028326f0471065","size":14560,"noattachment":false,"tarball":"https://registry.npmmirror.com/d3-brush/-/d3-brush-2.1.0.tgz","integrity":"sha512-cHLLAFatBATyIKqZOkk/mDHUbzne2B3ZwxkzMHvFTCZCmLaXDpZRihQSn8UNXTkGD/3lb/W2sQz0etAftmHMJQ=="},"_hasShrinkwrap":false,"_npmUser":{"name":"recifs","email":"fil@rezo.net"}},"2.0.1":{"name":"d3-brush","version":"2.0.1","dependencies":{"d3-dispatch":"1 - 2","d3-drag":"2","d3-interpolate":"1 - 2","d3-selection":"2","d3-transition":"2"},"devDependencies":{"eslint":"6","rollup":"1","rollup-plugin-terser":"5","tape":"4"},"directories":{},"dist":{"shasum":"668ea92f6511e6b4681ee844124276acd0a4acff","size":14454,"noattachment":false,"tarball":"https://registry.npmmirror.com/d3-brush/-/d3-brush-2.0.1.tgz","integrity":"sha512-QTSMtQAkFZy7e3kcrxHcR0HWVHa0hNngVdA+EvC52lIsq759KPAVWKV4kAB5G+Z7PBWYMGdvC8SchpJKw11jUA=="},"_hasShrinkwrap":false,"_npmUser":{"name":"recifs","email":"fil@rezo.net"}},"2.0.0":{"name":"d3-brush","version":"2.0.0","dependencies":{"d3-dispatch":"1 - 2","d3-drag":"2","d3-interpolate":"1 - 2","d3-selection":"2","d3-transition":"2"},"devDependencies":{"eslint":"6","rollup":"1","rollup-plugin-terser":"5","tape":"4"},"directories":{},"dist":{"shasum":"b20fca926f29ad4342fab4f87b76770810f44d16","size":14430,"noattachment":false,"tarball":"https://registry.npmmirror.com/d3-brush/-/d3-brush-2.0.0.tgz","integrity":"sha512-6j6WlvjsCC4whOctLfda8qRcrARwVfPlWmYXhrpazHK19GOjpN6CyWw9rP6bL3iXSj/aj3weLLKaGFQwd65KXg=="},"_hasShrinkwrap":false,"_npmUser":{"name":"recifs","email":"fil@rezo.net"}},"1.1.6":{"name":"d3-brush","version":"1.1.6","dependencies":{"d3-dispatch":"1","d3-drag":"1","d3-interpolate":"1","d3-selection":"1","d3-transition":"1"},"devDependencies":{"eslint":"6","rollup":"1","rollup-plugin-terser":"5","tape":"4"},"directories":{},"dist":{"shasum":"b0a22c7372cabec128bdddf9bddc058592f89e9b","size":13776,"noattachment":false,"tarball":"https://registry.npmmirror.com/d3-brush/-/d3-brush-1.1.6.tgz","integrity":"sha512-7RW+w7HfMCPyZLifTz/UnJmI5kdkXtpCbombUSs8xniAyo0vIbrDzDwUJB6eJOgl9u5DQOt2TQlYumxzD1SvYA=="},"_hasShrinkwrap":false,"_npmUser":{"name":"recifs","email":"fil@rezo.net"}},"2.0.0-rc.1":{"name":"d3-brush","version":"2.0.0-rc.1","dependencies":{"d3-dispatch":">=2.0.0-rc.1","d3-drag":">=2.0.0-rc.1","d3-interpolate":">=2.0.0-rc.1","d3-selection":">=2.0.0-rc.3","d3-transition":">=2.0.0-rc.1"},"devDependencies":{"eslint":"6","rollup":"1","rollup-plugin-terser":"5","tape":"4"},"directories":{},"dist":{"shasum":"47caafb86059b7cb97eeee7f46b8a5e2c8df9247","size":14451,"noattachment":false,"tarball":"https://registry.npmmirror.com/d3-brush/-/d3-brush-2.0.0-rc.1.tgz","integrity":"sha512-JUL6V+fa4j9eY1kg7Uj7zOfbXEPNCxd6OeI88FLHanc7cGgnEpfvdWojbs9iizvxtR8BEAYJimYrzlQ+vjfDnw=="},"_hasShrinkwrap":false,"_npmUser":{"name":"recifs","email":"fil@rezo.net"}},"1.1.5":{"name":"d3-brush","version":"1.1.5","dependencies":{"d3-dispatch":"1","d3-drag":"1","d3-interpolate":"1","d3-selection":"1","d3-transition":"1"},"devDependencies":{"eslint":"6","rollup":"1","rollup-plugin-terser":"5","tape":"4"},"directories":{},"dist":{"shasum":"066b8e84d17b192986030446c97c0fba7e1bacdc","size":13839,"noattachment":false,"tarball":"https://registry.npmmirror.com/d3-brush/-/d3-brush-1.1.5.tgz","integrity":"sha512-rEaJ5gHlgLxXugWjIkolTA0OyMvw8UWU1imYXy1v642XyyswmI1ybKOv05Ft+ewq+TFmdliD3VuK0pRp1VT/5A=="},"_hasShrinkwrap":false,"_npmUser":{"name":"mbostock","email":"mike@ocks.org"}},"1.1.4":{"name":"d3-brush","version":"1.1.4","dependencies":{"d3-dispatch":"1","d3-drag":"1","d3-interpolate":"1","d3-selection":"1","d3-transition":"1"},"devDependencies":{"eslint":"6","rollup":"1","rollup-plugin-terser":"5","tape":"4"},"directories":{},"dist":{"shasum":"a457887f558eb094b07d3db5c633facac6bd4cc4","size":13594,"noattachment":false,"tarball":"https://registry.npmmirror.com/d3-brush/-/d3-brush-1.1.4.tgz","integrity":"sha512-DRcFXGcVZiJF644i78m/HM8P0U19hWYRFcAnacOVGvpOpzkqGm3H0EAoAH6jwyY/lqfH49d+5vz2TgznP/zlMA=="},"_hasShrinkwrap":false,"_npmUser":{"name":"mbostock","email":"mike@ocks.org"}},"1.1.3":{"name":"d3-brush","version":"1.1.3","dependencies":{"d3-dispatch":"1","d3-drag":"1","d3-interpolate":"1","d3-selection":"1","d3-transition":"1"},"devDependencies":{"eslint":"6","rollup":"1","rollup-plugin-terser":"5","tape":"4"},"directories":{},"dist":{"shasum":"a04900a71fa5390f7f7afe1504b02a382709f380","size":13603,"noattachment":false,"tarball":"https://registry.npmmirror.com/d3-brush/-/d3-brush-1.1.3.tgz","integrity":"sha512-v8bbYyCFKjyCzFk/tdWqXwDykY8YWqhXYjcYxfILIit085VZOpj4XJKOMccTsvWxgzSLMJQg5SiqHjslsipEDg=="},"_hasShrinkwrap":false,"_npmUser":{"name":"mbostock","email":"mike@ocks.org"}},"1.1.3-rc.1":{"name":"d3-brush","version":"1.1.3-rc.1","dependencies":{"d3-dispatch":"1","d3-drag":"1","d3-interpolate":"1","d3-selection":"1","d3-transition":"1"},"devDependencies":{"eslint":"6","rollup":"1","rollup-plugin-terser":"5","tape":"4"},"directories":{},"dist":{"shasum":"c5720701c735f8558aaacecab0ee5c2f7e912d2c","size":13493,"noattachment":false,"tarball":"https://registry.npmmirror.com/d3-brush/-/d3-brush-1.1.3-rc.1.tgz","integrity":"sha512-8nRq3/WrMCUfZlvaqF+GPZLF7y2pKVIVGuR3rGPt6FBrygAOCfETSFdhvTxCUD1JBEg3+aWteT57JlDeuoR3SA=="},"_hasShrinkwrap":false,"_npmUser":{"name":"mbostock","email":"mike@ocks.org"}},"1.1.2":{"name":"d3-brush","version":"1.1.2","dependencies":{"d3-dispatch":"1","d3-drag":"1","d3-interpolate":"1","d3-selection":"1","d3-transition":"1"},"devDependencies":{"eslint":"6","rollup":"1","rollup-plugin-terser":"5","tape":"4"},"directories":{},"dist":{"shasum":"1d45941457d6903a1924f5c56c60363fed0e7bc9","size":13599,"noattachment":false,"tarball":"https://registry.npmmirror.com/d3-brush/-/d3-brush-1.1.2.tgz","integrity":"sha512-0cQBYrlKqLevZZaRE5Hh3W5FGp3c9gvUyJZm3B0Z3iAM3aSkEXt7F+4+vYyJoaL6vEipVM511rMqO3lD6ShyRA=="},"_hasShrinkwrap":false,"_npmUser":{"name":"mbostock","email":"mike@ocks.org"}},"1.1.1":{"name":"d3-brush","version":"1.1.1","dependencies":{"d3-dispatch":"1","d3-drag":"1","d3-interpolate":"1","d3-selection":"1","d3-transition":"1"},"devDependencies":{"eslint":"6","rollup":"1","rollup-plugin-terser":"5","tape":"4"},"directories":{},"dist":{"shasum":"4b31ff06b1c9dfca1b66d340d2afb0cdbc391d61","size":13577,"noattachment":false,"tarball":"https://registry.npmmirror.com/d3-brush/-/d3-brush-1.1.1.tgz","integrity":"sha512-nVIsduqChMBemov7NvTj3imYvDcihqf73RzoLULW0FrDmIlaWuP8Q9P+rPQB5SpqQjbrr4m0DoaHQewVcPhZsQ=="},"_hasShrinkwrap":false,"_npmUser":{"name":"mbostock","email":"mike@ocks.org"}},"1.1.0":{"name":"d3-brush","version":"1.1.0","dependencies":{"d3-dispatch":"1","d3-drag":"1","d3-interpolate":"1","d3-selection":"1","d3-transition":"1"},"devDependencies":{"eslint":"6","rollup":"1","rollup-plugin-terser":"5","tape":"4"},"directories":{},"dist":{"shasum":"458ac2c607a481aa8d57ced1788ae54ed59befae","size":13467,"noattachment":false,"tarball":"https://registry.npmmirror.com/d3-brush/-/d3-brush-1.1.0.tgz","integrity":"sha512-rbxi2Cuveuy53isbHpoF56TYDP4ZP8feFzxVSMtG+aGCL+TKVtm83yKPJBgcQc2VKf2Kb55ODvRQwY0uRSbttg=="},"_hasShrinkwrap":false,"_npmUser":{"name":"mbostock","email":"mike@ocks.org"}},"1.1.0-rc.3":{"name":"d3-brush","version":"1.1.0-rc.3","dependencies":{"d3-dispatch":"1","d3-drag":"1","d3-interpolate":"1","d3-selection":"1","d3-transition":"1"},"devDependencies":{"eslint":"6","rollup":"1","rollup-plugin-terser":"5","tape":"4"},"directories":{},"dist":{"shasum":"a4d4bac2a152d4a728e2deb50f38c57ad6d2aca0","size":13218,"noattachment":false,"tarball":"https://registry.npmmirror.com/d3-brush/-/d3-brush-1.1.0-rc.3.tgz","integrity":"sha512-LYWoD5hG/lyFFX9q868hror2bR9CEGWoVmeS2sAESeUxqllCxsDqxSXAMLU+JtuQjpQUOQleRXdc3bl1ZgJ9jA=="},"_hasShrinkwrap":false,"_npmUser":{"name":"mbostock","email":"mike@ocks.org"}},"1.1.0-rc.2":{"name":"d3-brush","version":"1.1.0-rc.2","dependencies":{"d3-dispatch":"1","d3-drag":"1","d3-interpolate":"1","d3-selection":"1","d3-transition":"1"},"devDependencies":{"eslint":"6","rollup":"1","rollup-plugin-terser":"5","tape":"4"},"directories":{},"dist":{"shasum":"2c852301f078177ab9c34456d53347cf850c6b7d","size":13214,"noattachment":false,"tarball":"https://registry.npmmirror.com/d3-brush/-/d3-brush-1.1.0-rc.2.tgz","integrity":"sha512-0xx1iyxmKlIuAuFs+F8e7FKhmXAD1MIAJZWvnLtjPDElzfiN6wPxYA8nOGRhj2DiJxslZYORcvnSzVeu4IFKnw=="},"_hasShrinkwrap":false,"_npmUser":{"name":"mbostock","email":"mike@ocks.org"}},"1.1.0-rc.1":{"name":"d3-brush","version":"1.1.0-rc.1","dependencies":{"d3-dispatch":"1","d3-drag":"1","d3-interpolate":"1","d3-selection":"1","d3-transition":"1"},"devDependencies":{"eslint":"6","rollup":"1","rollup-plugin-terser":"5","tape":"4"},"directories":{},"dist":{"shasum":"0b8b5def1c08e6b0cac5542ba05b40b0e3ae92ba","size":13184,"noattachment":false,"tarball":"https://registry.npmmirror.com/d3-brush/-/d3-brush-1.1.0-rc.1.tgz","integrity":"sha512-YpFFCdPbilX0QNpNl/2IFHZ4TeMtozjSaOingXvCDhIsyB68sy9FJxeg88r4VlnM8tR2C+rXG6TFCr1cR0LktA=="},"_hasShrinkwrap":false,"_npmUser":{"name":"mbostock","email":"mike@ocks.org"}},"1.0.6":{"name":"d3-brush","version":"1.0.6","dependencies":{"d3-dispatch":"1","d3-drag":"1","d3-interpolate":"1","d3-selection":"1","d3-transition":"1"},"devDependencies":{"eslint":"5","rollup":"0.64","rollup-plugin-terser":"1","tape":"4"},"directories":{},"dist":{"shasum":"33691f2032d9db6c5d8cb684ff255a9883629e21","size":24106,"noattachment":false,"tarball":"https://registry.npmmirror.com/d3-brush/-/d3-brush-1.0.6.tgz","integrity":"sha512-lGSiF5SoSqO5/mYGD5FAeGKKS62JdA1EV7HPrU2b5rTX4qEJJtpjaGLJngjnkewQy7UnGstnFd3168wpf5z76w=="},"_hasShrinkwrap":false,"_npmUser":{"name":"mbostock","email":"mike@ocks.org"}},"1.0.5":{"name":"d3-brush","version":"1.0.5","dependencies":{"d3-dispatch":"1","d3-drag":"1","d3-interpolate":"1","d3-selection":"1","d3-transition":"1"},"devDependencies":{"eslint":"5","rollup":"0.64","rollup-plugin-terser":"1","tape":"4"},"directories":{},"dist":{"shasum":"dba79d0b7b8a259c1321f3b824bd623f2c4ee80d","size":24083,"noattachment":false,"tarball":"https://registry.npmmirror.com/d3-brush/-/d3-brush-1.0.5.tgz","integrity":"sha512-RqCyNrt4WjUxwx60dXSf0Ha1vzp/lC8F1SirMtvb3NMblZ/xNn1FlztL3EfdQlgS+0j7gJZV2chxwt5zex1I1A=="},"_hasShrinkwrap":false,"_npmUser":{"name":"mbostock","email":"mike@ocks.org"}},"1.0.4":{"name":"d3-brush","version":"1.0.4","dependencies":{"d3-dispatch":"1","d3-drag":"1","d3-interpolate":"1","d3-selection":"1","d3-transition":"1"},"devDependencies":{"eslint":"3","package-preamble":"0.0","rollup":"0.41","tape":"4","uglify-js":"^2.8.11"},"directories":{},"dist":{"shasum":"00c2f238019f24f6c0a194a26d41a1530ffe7bc4","size":137232,"noattachment":false,"tarball":"https://registry.npmmirror.com/d3-brush/-/d3-brush-1.0.4.tgz","integrity":"sha512-nUFueDzOlvwFvuOBynGSyJM7Wt1H9fKgJeoWFSg3ScS4c7FJBch92FKUJKum4xtgPYHdgH2C3bRg3GzSVltCJQ=="},"_hasShrinkwrap":false,"_npmUser":{"name":"mbostock","email":"mike@ocks.org"}},"1.0.3":{"name":"d3-brush","version":"1.0.3","dependencies":{"d3-dispatch":"1","d3-drag":"1","d3-interpolate":"1","d3-selection":"1","d3-transition":"1"},"devDependencies":{"eslint":"3","package-preamble":"0.0","rollup":"0.36","tape":"4","uglify-js":"2"},"directories":{},"dist":{"shasum":"4fa5374cc3b755d0990bf76b71b7a66417751c74","size":140365,"noattachment":false,"tarball":"https://registry.npmmirror.com/d3-brush/-/d3-brush-1.0.3.tgz","integrity":"sha512-QN1+vNKlASStaPCR8kEv9IbzZWQQIPkcHPhEyjCRnnUXLCYx3H1q9zKp3Ouz3vgAYXtE2QziIrBgpVnk8cKjWQ=="},"_hasShrinkwrap":false,"_npmUser":{"name":"mbostock","email":"mbostock@gmail.com"}},"1.0.2":{"name":"d3-brush","version":"1.0.2","dependencies":{"d3-dispatch":"1","d3-drag":"1","d3-interpolate":"1","d3-selection":"1","d3-transition":"1"},"devDependencies":{"eslint":"2","package-preamble":"0.0","rollup":"0.34","tape":"4","uglify-js":"2"},"directories":{},"dist":{"shasum":"c9a725d0d7f7d69245551ff96e264215e59a82eb","size":140102,"noattachment":false,"tarball":"https://registry.npmmirror.com/d3-brush/-/d3-brush-1.0.2.tgz","integrity":"sha512-+PVv7qAd0X/FPcQ2MVFj7uXMt62ymnwvDnOxFOjsHRB/ybcn0ayRyvSOSi+u3IxVlLvhD4jB39QwP6Yv19vcCQ=="},"_hasShrinkwrap":false,"_npmUser":{"name":"mbostock","email":"mbostock@gmail.com"}},"1.0.1":{"name":"d3-brush","version":"1.0.1","dependencies":{"d3-dispatch":"1","d3-drag":"1","d3-interpolate":"1","d3-selection":"1","d3-transition":"1"},"devDependencies":{"eslint":"2","package-preamble":"0.0","rollup":"0.33","tape":"4","uglify-js":"2"},"directories":{},"dist":{"shasum":"d457affc2671a54cc1cc5429eff6c4c00bd0c8e3","size":140091,"noattachment":false,"tarball":"https://registry.npmmirror.com/d3-brush/-/d3-brush-1.0.1.tgz","integrity":"sha512-IHjB0Hd+6Sry0XWZ8zm2IAVgK6kN3GD1bpw36JjZXM04nBDF3waFolDHhAfP9YvHDfcCrbeTBjI0x16y7ocUxA=="},"_hasShrinkwrap":false,"_npmUser":{"name":"mbostock","email":"mbostock@gmail.com"}},"1.0.0":{"name":"d3-brush","version":"1.0.0","dependencies":{"d3-dispatch":"1","d3-drag":"1","d3-interpolate":"1","d3-selection":"1","d3-transition":"1"},"devDependencies":{"eslint":"2","package-preamble":"0.0","rollup":"0.33","tape":"4","uglify-js":"2"},"directories":{},"dist":{"shasum":"ad16b42bbac50f099e1ca1794087b877e1ffd738","size":140080,"noattachment":false,"tarball":"https://registry.npmmirror.com/d3-brush/-/d3-brush-1.0.0.tgz","integrity":"sha512-ClrQiak7X5l1jTti+ZOVlWaatu70gyCylDLFAxE4sIgIm23lBE7EQVTUa/uC60Idz2A4jb9eHs/TH1u+nzGLgQ=="},"_hasShrinkwrap":false,"_npmUser":{"name":"mbostock","email":"mbostock@gmail.com"}},"0.2.3":{"name":"d3-brush","version":"0.2.3","dependencies":{"d3-dispatch":"1","d3-drag":"~0.3.1","d3-interpolate":"1","d3-selection":"~0.9.0","d3-transition":"~0.3.0"},"devDependencies":{"eslint":"2","package-preamble":"0.0","rollup":"0.31","tape":"4","uglify-js":"2"},"directories":{},"dist":{"shasum":"03696cf89a8e1f7aea4fa9e015b7e92f3f5630d0","size":138025,"noattachment":false,"tarball":"https://registry.npmmirror.com/d3-brush/-/d3-brush-0.2.3.tgz","integrity":"sha512-ys4R/99e1a+kMORRLpVGWIIFmzhNHFr0b0E02hZqxRl+7AMmpYQjgn52sgLNlPNucCAob+RbjrSwEQxnl7pYnA=="},"_hasShrinkwrap":false,"_npmUser":{"name":"mbostock","email":"mike@ocks.org"}},"0.2.2":{"name":"d3-brush","version":"0.2.2","dependencies":{"d3-dispatch":"~0.5.0","d3-drag":"~0.3.0","d3-interpolate":"~0.9.0","d3-selection":"~0.8.0","d3-transition":"~0.3.0"},"devDependencies":{"eslint":"2","package-preamble":"0.0","rollup":"0.27","tape":"4","uglify-js":"2"},"directories":{},"dist":{"shasum":"231e128d3740910f9542907675ed571d5baa4948","size":140093,"noattachment":false,"tarball":"https://registry.npmmirror.com/d3-brush/-/d3-brush-0.2.2.tgz","integrity":"sha512-0ezR92CJPIRPRwQo+akM6Nlr4tukeWKHpf1Tx6Eiox/0v6e0DdhZc8gRpLLLh0e6bvxgHP12E/Oji8z5dyjbEg=="},"_hasShrinkwrap":false,"_npmUser":{"name":"mbostock","email":"mbostock@gmail.com"}},"0.2.1":{"name":"d3-brush","version":"0.2.1","dependencies":{"d3-dispatch":"~0.5.0","d3-drag":"~0.3.0","d3-interpolate":"~0.9.0","d3-selection":"~0.8.0","d3-transition":"~0.3.0"},"devDependencies":{"eslint":"2","package-preamble":"0.0","rollup":"0.27","tape":"4","uglify-js":"2"},"directories":{},"dist":{"shasum":"571070e43cbfd9000e0c7d2d0b7e9f2d7fb9854b","size":140096,"noattachment":false,"tarball":"https://registry.npmmirror.com/d3-brush/-/d3-brush-0.2.1.tgz","integrity":"sha512-y1n1BTyXN7l4pM7pMMTDa4okjFPntWfbnZDjWGbL0i3xdehcA12cwA6csHNzDs2HlK1gwbrOjJOHnjKWJq1DNw=="},"_hasShrinkwrap":false,"_npmUser":{"name":"mbostock","email":"mbostock@gmail.com"}},"0.2.0":{"name":"d3-brush","version":"0.2.0","dependencies":{"d3-dispatch":"~0.5.0","d3-drag":"~0.3.0","d3-interpolate":"~0.9.0","d3-selection":"~0.8.0","d3-transition":"~0.3.0"},"devDependencies":{"eslint":"2","package-preamble":"0.0","rollup":"0.27","tape":"4","uglify-js":"2"},"directories":{},"dist":{"shasum":"ef50eeeb1c37e951aceefaad9d0dc0dc6586520f","size":132802,"noattachment":false,"tarball":"https://registry.npmmirror.com/d3-brush/-/d3-brush-0.2.0.tgz","integrity":"sha512-u2+3G25kHgctWHrmC2A6aMoeGSS0BogEjchpFb4plyAygTGL1nzNd/Uqrcn/kCi9uVb9/CuHbL4IPDzJ0MGXFg=="},"_hasShrinkwrap":false,"_npmUser":{"name":"mbostock","email":"mbostock@gmail.com"}},"0.1.6":{"name":"d3-brush","version":"0.1.6","dependencies":{"d3-dispatch":"~0.4.3","d3-drag":"~0.2.0","d3-interpolate":"~0.8.0","d3-selection":"~0.7.2","d3-transition":"~0.2.8"},"devDependencies":{"eslint":"2","json2module":"0.0","rollup":"0.26","tape":"4","uglify-js":"2"},"directories":{},"dist":{"shasum":"57c28daffe9a098449f5b28f76c7025829160cf8","size":134757,"noattachment":false,"tarball":"https://registry.npmmirror.com/d3-brush/-/d3-brush-0.1.6.tgz","integrity":"sha512-BVdw9nmOtXilbl82irHGbhE+30zuKMLigCE7DuJtUj2VvweHINCgsLL9+9NvURbJUXMYpkA57q9cFMYRDFgeFw=="},"_hasShrinkwrap":false,"_npmUser":{"name":"mbostock","email":"mbostock@gmail.com"}},"0.1.5":{"name":"d3-brush","version":"0.1.5","dependencies":{"d3-dispatch":"~0.4.3","d3-drag":"~0.2.0","d3-interpolate":"~0.8.0","d3-selection":"~0.7.2","d3-transition":"~0.2.8"},"devDependencies":{"eslint":"2","json2module":"0.0","rollup":"0.26","tape":"4","uglify-js":"2"},"directories":{},"dist":{"shasum":"8d7c66085b515aa815fdc631051e2fb4ce3ddf54","size":134761,"noattachment":false,"tarball":"https://registry.npmmirror.com/d3-brush/-/d3-brush-0.1.5.tgz","integrity":"sha512-kPyZaYZ6Cs4/cMXFzsJOOpstuHAFRcEozFcXr9Aifdv4B9k8yMgDAdwGAzM+DemXt7oPtsXvS37W/HIAkX6Fzg=="},"_hasShrinkwrap":false,"_npmUser":{"name":"mbostock","email":"mbostock@gmail.com"}},"0.1.4":{"name":"d3-brush","version":"0.1.4","dependencies":{"d3-dispatch":"~0.4.3","d3-drag":"~0.2.0","d3-interpolate":"~0.8.0","d3-selection":"~0.7.2","d3-transition":"~0.2.8"},"devDependencies":{"eslint":"2","json2module":"0.0","rollup":"0.26","tape":"4","uglify-js":"2"},"directories":{},"dist":{"shasum":"cfa0532da3600c98eb7429f83465796900fbfe58","size":134171,"noattachment":false,"tarball":"https://registry.npmmirror.com/d3-brush/-/d3-brush-0.1.4.tgz","integrity":"sha512-eiVh4kMR87rokskzT1c/nKrPCsALQgDVkomGVeno0E7PMV5aWGTAPqZdxNpyErmiF9U++QPL+vf2xJLuTlf4vw=="},"_hasShrinkwrap":false,"_npmUser":{"name":"mbostock","email":"mbostock@gmail.com"}},"0.1.3":{"name":"d3-brush","version":"0.1.3","dependencies":{"d3-dispatch":"~0.4.3","d3-drag":"~0.2.0","d3-interpolate":"~0.8.0","d3-selection":"~0.7.2","d3-transition":"~0.2.8"},"devDependencies":{"eslint":"2","json2module":"0.0","rollup":"0.26","tape":"4","uglify-js":"2"},"directories":{},"dist":{"shasum":"cc8831fb1f2f14de831ac222d2afdbfdf2c877ef","size":134165,"noattachment":false,"tarball":"https://registry.npmmirror.com/d3-brush/-/d3-brush-0.1.3.tgz","integrity":"sha512-+8QdqHxVgTMPcb02odQmIa9ZAK0DkBm26o78EkP+plGj1WEttAB5KikVxSRUQY8+g8gM2VaymcWXv6YM4Zcttw=="},"_hasShrinkwrap":false,"_npmUser":{"name":"mbostock","email":"mbostock@gmail.com"}},"0.1.2":{"name":"d3-brush","version":"0.1.2","dependencies":{"d3-dispatch":"~0.4.3","d3-drag":"~0.2.0","d3-interpolate":"~0.8.0","d3-selection":"~0.7.2","d3-transition":"~0.2.8"},"devDependencies":{"eslint":"2","json2module":"0.0","rollup":"0.26","tape":"4","uglify-js":"2"},"directories":{},"dist":{"shasum":"56f08133b35865c8ef9a0768848df7d16b6618a5","size":134158,"noattachment":false,"tarball":"https://registry.npmmirror.com/d3-brush/-/d3-brush-0.1.2.tgz","integrity":"sha512-8CrzTbw121scPuJcUZoFQPahKg4hTlFlVpX+Sd1HGkR4dKCSUN+Iub8t5gp4/qYOeGBGR98Ci8PgNFtNDAicaw=="},"_hasShrinkwrap":false,"_npmUser":{"name":"mbostock","email":"mbostock@gmail.com"}},"0.1.1":{"name":"d3-brush","version":"0.1.1","dependencies":{"d3-dispatch":"~0.4.3","d3-drag":"~0.2.0","d3-interpolate":"~0.8.0","d3-selection":"~0.7.2","d3-transition":"~0.2.8"},"devDependencies":{"eslint":"2","json2module":"0.0","rollup":"0.26","tape":"4","uglify-js":"2"},"directories":{},"dist":{"shasum":"e72f08fa649030ce1ca8dbe12b68a87a06f67559","size":134132,"noattachment":false,"tarball":"https://registry.npmmirror.com/d3-brush/-/d3-brush-0.1.1.tgz","integrity":"sha512-w23oX3dRUEovuReVAUQ942FIhITZfRWFRyAvl8uC4VClUG39c7APByYZoOJqixDKjETNRf2SCwMm6a14ijpgGg=="},"_hasShrinkwrap":false,"_npmUser":{"name":"mbostock","email":"mbostock@gmail.com"}},"0.1.0":{"name":"d3-brush","version":"0.1.0","dependencies":{"d3-dispatch":"~0.4.3","d3-drag":"~0.2.0","d3-interpolate":"~0.8.0","d3-selection":"~0.7.2","d3-transition":"~0.2.8"},"devDependencies":{"eslint":"2","json2module":"0.0","rollup":"0.26","tape":"4","uglify-js":"2"},"directories":{},"dist":{"shasum":"4866ec3f6dcecd998b72c82e1c5e9c0dd9163d5d","size":10219,"noattachment":false,"tarball":"https://registry.npmmirror.com/d3-brush/-/d3-brush-0.1.0.tgz","integrity":"sha512-NN+41NzCG7Iyv/1KUpnDvVzoZluB3DesJT3dMPbNmLXodTZ9FzRC2Uw4oFDnAPyuduJPNjY8m12OmPQ73NOX1w=="},"_hasShrinkwrap":false,"_npmUser":{"name":"mbostock","email":"mbostock@gmail.com"}},"0.0.4":{"name":"d3-brush","version":"0.0.4","dependencies":{"d3-transition":"~0.2.5"},"directories":{},"dist":{"shasum":"6fdf652561d3dd2df141274fe6a4be6e771c8fd2","size":5045,"noattachment":false,"tarball":"https://registry.npmmirror.com/d3-brush/-/d3-brush-0.0.4.tgz","integrity":"sha512-yjfrDWHJngDIIyf4U6P8JmqGOwjARoC8+82D9FLv+6CnFrhOhEAZ2MX0AGtG8OuOMuvgvoHWO8TOYuVGRfmgsQ=="},"_hasShrinkwrap":false,"_npmUser":{"name":"aqson","email":"aqson@me.com"}},"0.0.3":{"name":"d3-brush","version":"0.0.3","dependencies":{"d3-transition":"~0.2.5"},"directories":{},"dist":{"shasum":"f47fe03c5154a4c5a09f67863cdd94cbccf18bbf","size":5046,"noattachment":false,"tarball":"https://registry.npmmirror.com/d3-brush/-/d3-brush-0.0.3.tgz","integrity":"sha512-6Oe7fj4nASVcNkLYuqkWOCcbqufjAK4m6PiV2Gy7a5LMomV7VvQ9/pLoD7p3gkYK+VMhgGOhxizZVkh5gmwT4A=="},"_hasShrinkwrap":false,"_npmUser":{"name":"aqson","email":"aqson@me.com"}},"0.0.2":{"name":"d3-brush","version":"0.0.2","dependencies":{"d3-transition":"~0.2.5"},"directories":{},"dist":{"shasum":"7c1af28a2c946ec2c6db4999602a53fb2b21cc07","size":5038,"noattachment":false,"tarball":"https://registry.npmmirror.com/d3-brush/-/d3-brush-0.0.2.tgz","integrity":"sha512-3KF62dlZqSPJYJyni4p82RHRTejfMXbuZ3m+smoabkusKMefax0jJP6dJSK6hZ9F5xLKqvAqFWF35/50qKoeUg=="},"_hasShrinkwrap":false,"_npmUser":{"name":"aqson","email":"aqson@me.com"}},"0.0.1":{"name":"d3-brush","version":"0.0.1","dependencies":{},"directories":{},"dist":{"shasum":"a58a64d726f5e28187824f9ed92ce2934aa55fbd","size":4050,"noattachment":false,"tarball":"https://registry.npmmirror.com/d3-brush/-/d3-brush-0.0.1.tgz","integrity":"sha512-HtAwOeebT8GLhMt2lULvV2Lziuv5B0xprBg5m67OLFj5XDNJFIaD1XRgokFCCXvKpIMtUBksKThFEDr2ZQJLyg=="},"_hasShrinkwrap":false,"_npmUser":{"name":"aqson","email":"aqson@me.com"}}},"_source_registry_name":"default","cachedAt":1775979444099}