{"dist-tags":{"latest":"7.0.0"},"modified":"2024-05-28T08:35:41.451Z","name":"rehype-raw","versions":{"6.1.0":{"name":"rehype-raw","version":"6.1.0","dependencies":{"@types/hast":"^2.0.0","hast-util-raw":"^7.2.0","unified":"^10.0.0"},"devDependencies":{"@types/tape":"^4.0.0","c8":"^7.0.0","prettier":"^2.0.0","rehype-stringify":"^9.0.0","remark-cli":"^10.0.0","remark-parse":"^10.0.0","remark-preset-wooorm":"^9.0.0","remark-rehype":"^9.0.0","rimraf":"^3.0.0","tape":"^5.0.0","type-coverage":"^2.0.0","typescript":"^4.0.0","unist-util-visit":"^4.0.0","xo":"^0.44.0"},"directories":{},"dist":{"shasum":"78ba31d8725fe98467ca1acbbd65e2d0040b46e1","size":4262,"noattachment":false,"tarball":"https://registry.npmmirror.com/rehype-raw/-/rehype-raw-6.1.0.tgz","integrity":"sha512-12j2UiiYJgZFdjnHDny77NY5BF3eW4Jsl0vtgL1DWdTzcHjPpbhumU+GtPUdivEWwQc8x9OdEuO0oxaGz7Tvyg=="},"_hasShrinkwrap":false,"_npmUser":{"name":"wooorm","email":"tituswormer@gmail.com"},"funding":{"type":"opencollective","url":"https://opencollective.com/unified"}},"6.0.0":{"name":"rehype-raw","version":"6.0.0","dependencies":{"@types/hast":"^2.0.0","hast-util-raw":"^7.0.0","unified":"^10.0.0"},"devDependencies":{"@types/tape":"^4.0.0","c8":"^7.0.0","prettier":"^2.0.0","rehype-stringify":"^9.0.0","remark-cli":"^9.0.0","remark-parse":"^9.0.0","remark-preset-wooorm":"^8.0.0","remark-rehype":"^8.0.0","rimraf":"^3.0.0","tape":"^5.0.0","type-coverage":"^2.0.0","typescript":"^4.0.0","xo":"^0.42.0"},"directories":{},"dist":{"shasum":"7a176e73f7c452db7e8608b637355d566f61245e","size":4199,"noattachment":false,"tarball":"https://registry.npmmirror.com/rehype-raw/-/rehype-raw-6.0.0.tgz","integrity":"sha512-vzbvI7d3WUJHh+7aaHs0PHlgc+NevOh+buLkEB7I/FD3xskTmhUntnjS57uTW3uQt67xcF3COm9OwLpVsk6jvg=="},"_hasShrinkwrap":false,"_npmUser":{"name":"wooorm","email":"tituswormer@gmail.com"},"funding":{"type":"opencollective","url":"https://opencollective.com/unified"}},"5.1.0":{"name":"rehype-raw","version":"5.1.0","dependencies":{"hast-util-raw":"^6.1.0"},"devDependencies":{"browserify":"^17.0.0","dtslint":"^4.0.0","nyc":"^15.0.0","prettier":"^2.0.0","rehype-stringify":"^8.0.0","remark-cli":"^9.0.0","remark-parse":"^9.0.0","remark-preset-wooorm":"^8.0.0","remark-rehype":"^8.0.0","tape":"^5.0.0","tinyify":"^3.0.0","unified":"^9.0.0","xo":"^0.38.0"},"directories":{},"dist":{"shasum":"66d5e8d7188ada2d31bc137bc19a1000cf2c6b7e","size":3925,"noattachment":false,"tarball":"https://registry.npmmirror.com/rehype-raw/-/rehype-raw-5.1.0.tgz","integrity":"sha512-MDvHAb/5mUnif2R+0IPCYJU8WjHa9UzGtM/F4AVy5GixPlDZ1z3HacYy4xojDU+uBa+0X/3PIfyQI26/2ljJNA=="},"_hasShrinkwrap":false,"_npmUser":{"name":"wooorm","email":"tituswormer@gmail.com"},"funding":{"type":"opencollective","url":"https://opencollective.com/unified"}},"5.0.0":{"name":"rehype-raw","version":"5.0.0","dependencies":{"hast-util-raw":"^6.0.0"},"devDependencies":{"browserify":"^16.0.0","dtslint":"^4.0.0","nyc":"^15.0.0","prettier":"^2.0.0","rehype-stringify":"^8.0.0","remark-cli":"^8.0.0","remark-parse":"^8.0.0","remark-preset-wooorm":"^7.0.0","remark-rehype":"^7.0.0","tape":"^5.0.0","tinyify":"^3.0.0","unified":"^9.0.0","xo":"^0.33.0"},"directories":{},"dist":{"shasum":"3688e3e1132e958761e677a1b9b2ba358a465af8","size":3848,"noattachment":false,"tarball":"https://registry.npmmirror.com/rehype-raw/-/rehype-raw-5.0.0.tgz","integrity":"sha512-q/MOBj4fs1WF/LSCh5uOtNhnm5OESuDcSvq1mDQP4/2t6Q52E9MHeVoLeMy9vOn93BEcgVBm4FCokcK2iXRDvA=="},"_hasShrinkwrap":false,"_npmUser":{"name":"wooorm","email":"tituswormer@gmail.com"},"funding":{"type":"opencollective","url":"https://opencollective.com/unified"}},"4.0.2":{"name":"rehype-raw","version":"4.0.2","dependencies":{"hast-util-raw":"^5.0.0"},"devDependencies":{"browserify":"^16.0.0","nyc":"^15.0.0","prettier":"^1.0.0","rehype-stringify":"^6.0.0","remark-cli":"^7.0.0","remark-parse":"^7.0.0","remark-preset-wooorm":"^6.0.0","remark-rehype":"^5.0.0","tape":"^4.0.0","tinyify":"^2.0.0","unified":"^8.0.0","xo":"^0.28.0"},"directories":{},"dist":{"shasum":"5d3191689df96c8c651ce5f51a6c668d2c07b9c8","size":3729,"noattachment":false,"tarball":"https://registry.npmmirror.com/rehype-raw/-/rehype-raw-4.0.2.tgz","integrity":"sha512-xQt94oXfDaO7sK9mJBtsZXkjW/jm6kArCoYN+HqKZ51O19AFHlp3Xa5UfZZ2tJkbpAZzKtgVUYvnconk9IsFuA=="},"_hasShrinkwrap":false,"_npmUser":{"name":"wooorm","email":"tituswormer@gmail.com"},"funding":{"type":"opencollective","url":"https://opencollective.com/unified"}},"4.0.1":{"name":"rehype-raw","version":"4.0.1","dependencies":{"hast-util-raw":"^5.0.0"},"devDependencies":{"browserify":"^16.0.0","nyc":"^14.0.0","prettier":"^1.0.0","rehype-stringify":"^5.0.0","remark-cli":"^6.0.0","remark-parse":"^6.0.0","remark-preset-wooorm":"^5.0.0","remark-rehype":"^4.0.0","tape":"^4.0.0","tinyify":"^2.0.0","unified":"^7.0.0","xo":"^0.24.0"},"directories":{},"dist":{"shasum":"65e228469e129a2ca94fe47778132cb647fb9718","size":3567,"noattachment":false,"tarball":"https://registry.npmmirror.com/rehype-raw/-/rehype-raw-4.0.1.tgz","integrity":"sha512-g74dPCUWeB9EBfTfGF3lGOHSnZwFwN1ssc3Je9OwQO9f8yTkkAIrMqUVxT34h8zpi4ICU051tTLBZbOrzRWpxg=="},"_hasShrinkwrap":false,"_npmUser":{"name":"wooorm","email":"tituswormer@gmail.com"}},"4.0.0":{"name":"rehype-raw","version":"4.0.0","dependencies":{"hast-util-raw":"^5.0.0"},"devDependencies":{"browserify":"^16.0.0","nyc":"^13.0.0","prettier":"^1.13.7","rehype-stringify":"^4.0.0","remark-cli":"^6.0.0","remark-parse":"^6.0.0","remark-preset-wooorm":"^4.0.0","remark-rehype":"^3.0.0","tape":"^4.0.0","tinyify":"^2.4.3","unified":"^7.0.0","xo":"^0.23.0"},"directories":{},"dist":{"shasum":"0928f265af190eb23a42168f7485022e1763435a","size":2771,"noattachment":false,"tarball":"https://registry.npmmirror.com/rehype-raw/-/rehype-raw-4.0.0.tgz","integrity":"sha512-3fc6EGO7+fumyD7vQrvThsc8xuz7AzPzoAoGnCaTjyZOy/Gc1TBBouYWSjzZxEbW9dit2vq+op2Zyw2EOR0b2A=="},"_hasShrinkwrap":false,"_npmUser":{"name":"wooorm","email":"tituswormer@gmail.com"}},"3.0.0":{"name":"rehype-raw","version":"3.0.0","dependencies":{"hast-util-raw":"^4.0.0"},"devDependencies":{"browserify":"^16.0.0","nyc":"^12.0.0","prettier":"^1.13.7","rehype-stringify":"^4.0.0","remark-cli":"^5.0.0","remark-parse":"^5.0.0","remark-preset-wooorm":"^4.0.0","remark-rehype":"^3.0.0","tape":"^4.0.0","tinyify":"^2.4.3","unified":"^7.0.0","xo":"^0.21.0"},"directories":{},"dist":{"shasum":"74306a753379bff2b272a524905e0682e12df73c","size":2677,"noattachment":false,"tarball":"https://registry.npmmirror.com/rehype-raw/-/rehype-raw-3.0.0.tgz","integrity":"sha512-U8OBB1DwrsxK5trvrhZLaJWrFkTFtOaLV7z8O7OAnwJ/+VTNBEaTUgJfMihSxB063m7/eNVA4+yZnDVuTxeTrQ=="},"_hasShrinkwrap":false,"_npmUser":{"name":"wooorm","email":"tituswormer@gmail.com"}},"2.0.0":{"name":"rehype-raw","version":"2.0.0","dependencies":{"hast-util-raw":"^2.0.0"},"devDependencies":{"browserify":"^14.1.0","esmangle":"^1.0.0","nyc":"^11.0.0","rehype-stringify":"^3.0.0","remark-cli":"^3.0.0","remark-parse":"^3.0.0","remark-preset-wooorm":"^3.0.0","remark-rehype":"^2.0.0","tape":"^4.0.0","unified":"^6.0.0","xo":"^0.18.0"},"directories":{},"dist":{"shasum":"5637a9fceef34800fd7c57ca32fd9d5927fd2aaa","size":2434,"noattachment":false,"tarball":"https://registry.npmmirror.com/rehype-raw/-/rehype-raw-2.0.0.tgz","integrity":"sha512-CJ2ko7jPX1W2AV57Fpb8hepYxmAyzKJ78DKNoz/ZtK3Sf7Z1XZuOo53qCEj6VVlB5HzrO+Q7dU/SYeNqG3+lFQ=="},"_hasShrinkwrap":false,"_npmUser":{"name":"wooorm","email":"tituswormer@gmail.com"}},"1.0.0":{"name":"rehype-raw","version":"1.0.0","dependencies":{"hast-util-raw":"^1.0.0"},"devDependencies":{"browserify":"^13.0.0","esmangle":"^1.0.0","nyc":"^8.3.1","rehype-stringify":"^2.0.0","remark-cli":"^2.0.0","remark-parse":"^2.0.2","remark-preset-wooorm":"^1.0.0","remark-rehype":"^1.1.0","tape":"^4.0.0","unified":"^5.1.0","xo":"^0.17.0"},"directories":{},"dist":{"shasum":"6f2f8ebe6858f8304dfe2704ccc6cb29ae8d858e","size":2433,"noattachment":false,"tarball":"https://registry.npmmirror.com/rehype-raw/-/rehype-raw-1.0.0.tgz","integrity":"sha512-t1Yw0QqBERZ1199bw2M+NosGzq+pi0kaLbQntVoN5VFWi+XO/c63nI8hbfahzEAmRVND8tz/URfwgqErzP9Fsg=="},"_hasShrinkwrap":false,"_npmUser":{"name":"wooorm","email":"tituswormer@gmail.com"}},"6.1.1":{"name":"rehype-raw","version":"6.1.1","dependencies":{"@types/hast":"^2.0.0","hast-util-raw":"^7.2.0","unified":"^10.0.0"},"devDependencies":{"@types/tape":"^4.0.0","c8":"^7.0.0","prettier":"^2.0.0","rehype-stringify":"^9.0.0","remark-cli":"^10.0.0","remark-parse":"^10.0.0","remark-preset-wooorm":"^9.0.0","remark-rehype":"^10.0.0","rimraf":"^3.0.0","tape":"^5.0.0","type-coverage":"^2.0.0","typescript":"^4.0.0","unist-util-visit":"^4.0.0","xo":"^0.47.0"},"directories":{},"dist":{"integrity":"sha512-d6AKtisSRtDRX4aSPsJGTfnzrX2ZkHQLE5kiUuGOeEoLpbEulFF4hj0mLPbsa+7vmguDKOVVEQdHKDSwoaIDsQ==","shasum":"81bbef3793bd7abacc6bf8335879d1b6c868c9d4","tarball":"https://registry.npmmirror.com/rehype-raw/-/rehype-raw-6.1.1.tgz","fileCount":5,"unpackedSize":11756,"npm-signature":"-----BEGIN PGP SIGNATURE-----\r\nVersion: OpenPGP.js v3.0.13\r\nComment: https://openpgpjs.org\r\n\r\nwsFcBAEBCAAQBQJhzZ+mCRA9TVsSAnZWagAAmcgP/0+k3sm3y78iQQr11+rr\ndOMAKwNjWNGC6CvAVOqsA7csMCBC+xAIjy4cJG9NvVsLL3zOdl8bcXJnLws8\nEiUlABqyQ17XV6AiTc58sn6ksfJJFd4vL8SdZQex/UW0f0g9gsck+9w6SeUr\nfB9oPUiILqgN/+RMdgHtKrxp1NeyPrsTswiYtyD+Y/c/v44i7YvGs+73cZO+\nQ5MZfsIb3rdw5YBAr3E5Gd5q5cNwpPhsMNHOLoQvTrDd8p/tSK67BPyjbUNn\nhQyIN8TN49oFLsNO0Sa6gQpCgOS7UBY2idQ2XE95Q2ufIYdZ5AzjEXHJrnvu\nZel5ehhMCBKFLfPQWFyT1MjrQpu8V9oLDaZOKboH+I1BTfdN4bpt7YbDe80A\nYvTmX7sdGGcUdv+PLk0r0eGRAb6myTeSlsRdM5ewe3jYmhM6J7/E29LpajgN\nTMlbLCdfN1uQD566Cx+b7kdRr324i/jupyjF0bRqAVHDezaEVSuCmJEBvB2n\n6FADgS9cS7O5vz/x7HLPgT8yQnYlprGvN6VmdZ8uxt7MzeBTP3wXMVZzeJlR\npTkK/SdYJVw/0M8f6sYeOpqS7jVChvH78mvwdMtCAFbk7ZddrmwNsU10dJgB\nNKLQcYX1Dr5CXPPK8T9CYwtYDEcTp1uEND6YZScJlTZPzDD7VEMzqH1EgL2T\nm8Bd\r\n=fqKl\r\n-----END PGP SIGNATURE-----\r\n","size":4870},"_hasShrinkwrap":false,"_npmUser":{"name":"wooorm","email":"tituswormer@gmail.com"},"funding":{"type":"opencollective","url":"https://opencollective.com/unified"}},"7.0.0":{"name":"rehype-raw","version":"7.0.0","dependencies":{"@types/hast":"^3.0.0","hast-util-raw":"^9.0.0","vfile":"^6.0.0"},"devDependencies":{"@types/node":"^20.0.0","c8":"^8.0.0","prettier":"^3.0.0","rehype-stringify":"^10.0.0","remark-cli":"^11.0.0","remark-parse":"^10.0.0","remark-preset-wooorm":"^9.0.0","remark-rehype":"^10.0.0","type-coverage":"^2.0.0","typescript":"^5.0.0","unified":"^11.0.0","unist-util-visit":"^5.0.0","xo":"^0.56.0"},"directories":{},"dist":{"integrity":"sha512-/aE8hCfKlQeA8LmyeyQvQF3eBiLRGNlfBJEvWH7ivp9sBqs7TNqBL5X3v157rM4IFETqDnIOO+z5M/biZbo9Ww==","shasum":"59d7348fd5dbef3807bbaa1d443efd2dd85ecee4","tarball":"https://registry.npmmirror.com/rehype-raw/-/rehype-raw-7.0.0.tgz","fileCount":7,"unpackedSize":12527,"signatures":[{"keyid":"SHA256:jl3bwswu80PjjokCgh0o2w5c2U4LhQAE57gj9cz1kzA","sig":"MEQCIBFEMoE9rklLyIjnjn763wp14cRLdwD/6QLS5ZFFKwHWAiBcBFtDyuqxzQKk5t6m/r2b+1iYcMi9kOTbEAwpDbZogA=="}],"size":5099},"_hasShrinkwrap":false,"publish_time":1693044227145,"_source_registry_name":"default","funding":{"type":"opencollective","url":"https://opencollective.com/unified"}}},"_source_registry_name":"default","cachedAt":1775979277559}