{"dist-tags":{"latest":"7946.0.16","ts2.0":"1.0.5","ts2.1":"1.0.5","ts2.2":"1.0.5","ts2.3":"7946.0.7","ts2.4":"7946.0.7","ts2.5":"7946.0.7","ts2.6":"7946.0.7","ts2.7":"7946.0.7","ts2.8":"7946.0.7","ts2.9":"7946.0.7","ts3.0":"7946.0.7","ts3.1":"7946.0.7","ts3.2":"7946.0.7","ts3.3":"7946.0.7","ts3.4":"7946.0.7","ts3.5":"7946.0.7","ts3.6":"7946.0.8","ts3.7":"7946.0.8","ts3.8":"7946.0.8","ts3.9":"7946.0.8","ts4.0":"7946.0.10","ts4.1":"7946.0.10","ts4.2":"7946.0.10","ts4.3":"7946.0.10","ts4.4":"7946.0.10","ts4.5":"7946.0.13","ts4.6":"7946.0.14","ts4.7":"7946.0.14","ts4.8":"7946.0.14","ts4.9":"7946.0.14","ts5.0":"7946.0.16","ts5.1":"7946.0.16","ts5.2":"7946.0.16","ts5.3":"7946.0.16","ts5.4":"7946.0.16","ts5.5":"7946.0.16","ts5.6":"7946.0.16","ts5.7":"7946.0.16","ts5.8":"7946.0.16","ts5.9":"7946.0.16","ts6.0":"7946.0.16"},"modified":"2025-08-03T06:52:52.779Z","name":"@types/geojson","versions":{"7946.0.8":{"name":"@types/geojson","version":"7946.0.8","dependencies":{},"directories":{},"dist":{"shasum":"30744afdb385e2945e22f3b033f897f76b1f12ca","size":2924,"noattachment":false,"tarball":"https://registry.npmmirror.com/@types/geojson/-/geojson-7946.0.8.tgz","integrity":"sha512-1rkryxURpr6aWP7R786/UQOkJ3PcpQiWkAXBmdWc7ryFWqN6a4xfK7BtjXvFBKO9LjQ+MWQSWxYeZX1OApnArA=="},"_hasShrinkwrap":false,"_npmUser":{"name":"types","email":"ts-npm-types@microsoft.com"}},"7946.0.7":{"name":"@types/geojson","version":"7946.0.7","dependencies":{},"directories":{},"dist":{"shasum":"c8fa532b60a0042219cdf173ca21a975ef0666ad","size":2881,"noattachment":false,"tarball":"https://registry.npmmirror.com/@types/geojson/-/geojson-7946.0.7.tgz","integrity":"sha512-wE2v81i4C4Ol09RtsWFAqg3BUitWbHSpSlIo+bNdsCJijO9sjme+zm+73ZMCa/qMC8UEERxzGbvmr1cffo2SiQ=="},"_hasShrinkwrap":false,"_npmUser":{"name":"types","email":"ts-npm-types@microsoft.com"}},"7946.0.6":{"name":"@types/geojson","version":"7946.0.6","dependencies":{},"directories":{},"dist":{"shasum":"416f388a06b227784a2d91a88a53f14de05cd54b","size":2877,"noattachment":false,"tarball":"https://registry.npmmirror.com/@types/geojson/-/geojson-7946.0.6.tgz","integrity":"sha512-f6qai3iR62QuMPPdgyH+LyiXTL2n9Rf62UniJjV7KHrbiwzLTZUKsdq0mFSTxAHbO7JvwxwC4tH0m1UnweuLrA=="},"_hasShrinkwrap":false,"_npmUser":{"name":"types","email":"ts-npm-types@microsoft.com"}},"7946.0.5":{"name":"@types/geojson","version":"7946.0.5","dependencies":{},"directories":{},"dist":{"shasum":"9aea839ea5af4b1bc079f1d9fa977d48665e02b0","size":2861,"noattachment":false,"tarball":"https://registry.npmmirror.com/@types/geojson/-/geojson-7946.0.5.tgz","integrity":"sha512-rLlMXpd3rdlrp0+xsrda/hFfOpIxgqFcRpk005UKbHtcdFK+QXAjhBAPnvO58qF4O1LdDXrcaiJxMgstCIlcaw=="},"_hasShrinkwrap":false,"_npmUser":{"name":"types","email":"ts-npm-types@microsoft.com"}},"7946.0.4":{"name":"@types/geojson","version":"7946.0.4","dependencies":{},"directories":{},"dist":{"shasum":"4e049756383c3f055dd8f3d24e63fb543e98eb07","size":2762,"noattachment":false,"tarball":"https://registry.npmmirror.com/@types/geojson/-/geojson-7946.0.4.tgz","integrity":"sha512-MHmwBtCb7OCv1DSivz2UNJXPGU/1btAWRKlqJ2saEhVJkpkvqHMMaOpKg0v4sAbDWSQekHGvPVMM8nQ+Jen03Q=="},"_hasShrinkwrap":false,"_npmUser":{"name":"types","email":"ts-npm-types@microsoft.com"}},"7946.0.3":{"name":"@types/geojson","version":"7946.0.3","dependencies":{},"directories":{},"dist":{"shasum":"e5791534ab0acfb2b3a39b713966cfcee85d469f","size":2774,"noattachment":false,"tarball":"https://registry.npmmirror.com/@types/geojson/-/geojson-7946.0.3.tgz","integrity":"sha512-BYHiG1vQJ7T93uswzuXZ0OBPWqj5tsAPtaMDQADV8sn2InllXarwg9llr6uaW22q1QCwBZ81gVajOpYWzjesug=="},"_hasShrinkwrap":false,"_npmUser":{"name":"types","email":"ts-npm-types@microsoft.com"}},"7946.0.2":{"name":"@types/geojson","version":"7946.0.2","dependencies":{},"directories":{},"dist":{"shasum":"0bd0a01ef04e813c2b7580318da9e37c2eadea9c","size":2691,"noattachment":false,"tarball":"https://registry.npmmirror.com/@types/geojson/-/geojson-7946.0.2.tgz","integrity":"sha512-JuRe9eeID7XvL7viIcFqIAAXDLfyRcImIWE/XjBIhrUZjxX5z4fLcF3QXS9zYnvIn8mmtW/7OxDV3XC8QMb7OA=="},"_hasShrinkwrap":false,"_npmUser":{"name":"types","email":"ts-npm-types@microsoft.com"}},"7946.0.1":{"name":"@types/geojson","version":"7946.0.1","dependencies":{},"directories":{},"dist":{"shasum":"1fc41280e42f08f0d568401a556bc97c34f5262e","size":2689,"noattachment":false,"tarball":"https://registry.npmmirror.com/@types/geojson/-/geojson-7946.0.1.tgz","integrity":"sha512-BXY6tH16Snp/ZdX6cFlBD8yfEArcZemzxEGciXkMmp1/tU76oyqkxJq91JQzT8SXWzRPwj//dw0/FdCSnnT8mw=="},"_hasShrinkwrap":false,"_npmUser":{"name":"types","email":"ts-npm-types@microsoft.com"}},"7946.0.0":{"name":"@types/geojson","version":"7946.0.0","dependencies":{},"directories":{},"dist":{"shasum":"e8bc74e8183d966455f82023f0c72e1072a952d0","size":2679,"noattachment":false,"tarball":"https://registry.npmmirror.com/@types/geojson/-/geojson-7946.0.0.tgz","integrity":"sha512-lbWmXFxIpEzpH7OprsCRvxj7kie+248Y2ItjeVsF+0+IqvwG+R+0xgZmxq1ofYNTszvuihDahas7O5dscfxTsw=="},"_hasShrinkwrap":false,"_npmUser":{"name":"types","email":"ts-npm-types@microsoft.com"}},"1.0.6":{"name":"@types/geojson","version":"1.0.6","dependencies":{},"directories":{},"dist":{"shasum":"3e02972728c69248c2af08d60a48cbb8680fffdf","size":2079,"noattachment":false,"tarball":"https://registry.npmmirror.com/@types/geojson/-/geojson-1.0.6.tgz","integrity":"sha512-Xqg/lIZMrUd0VRmSRbCAewtwGZiAk3mEUDvV4op1tGl+LvyPcb/MIOSxTl9z+9+J+R4/vpjiCAT4xeKzH9ji1w=="},"_hasShrinkwrap":false,"_npmUser":{"name":"types","email":"ts-npm-types@microsoft.com"}},"1.0.5":{"name":"@types/geojson","version":"1.0.5","dependencies":{},"directories":{},"dist":{"shasum":"ef9f12277233399c7f32086818a56a84c8952f8f","size":2017,"noattachment":false,"tarball":"https://registry.npmmirror.com/@types/geojson/-/geojson-1.0.5.tgz","integrity":"sha512-Vv/xcob92T/Vncg/AvPMYS0R2a+PYBnnTGNb7bE8jyqEXqq08Tp1frhx6+ExKCImyQq6iLfqjeXt/Wtsh8Sjgw=="},"_hasShrinkwrap":false,"_npmUser":{"name":"types","email":"ts-npm-types@microsoft.com"}},"1.0.4":{"name":"@types/geojson","version":"1.0.4","dependencies":{},"directories":{},"dist":{"shasum":"f6e011bf3f7eea616cce79b6f1a0722010822f3a","size":1981,"noattachment":false,"tarball":"https://registry.npmmirror.com/@types/geojson/-/geojson-1.0.4.tgz","integrity":"sha512-idP+xKlqFG1egc5M52mDat/Z0VMrwY93LCd81dzW/IjeTIYTMWuzVu+fBf19QK/mX9K7jM2UNN5nzDRgM950GA=="},"_hasShrinkwrap":false,"_npmUser":{"name":"types","email":"ts-npm-types@microsoft.com"}},"1.0.3":{"name":"@types/geojson","version":"1.0.3","dependencies":{},"directories":{},"dist":{"shasum":"fbcf7fa5eb6dd108d51385cc6987ec1f24214523","size":1972,"noattachment":false,"tarball":"https://registry.npmmirror.com/@types/geojson/-/geojson-1.0.3.tgz","integrity":"sha512-unWrGQhXRrNTk/MabfBLCM/rWT6zxR1OSK0GIPxsP8NX8mJcsNWkERPp4z0pTyHLiANy+Nwczf8Q2I16Pth1FA=="},"_hasShrinkwrap":false,"_npmUser":{"name":"types","email":"ts-npm-types@microsoft.com"}},"1.0.2":{"name":"@types/geojson","version":"1.0.2","dependencies":{},"peerDependencies":{},"directories":{},"dist":{"shasum":"b02d10ab028e2928ac592a051aaa4981a1941d03","size":1974,"noattachment":false,"tarball":"https://registry.npmmirror.com/@types/geojson/-/geojson-1.0.2.tgz","integrity":"sha512-hUQCkTRtf954WoHhyFkYYE88HyyyBPlZEeXElxxv6JP+uPqZjixE4QRmuRztmpLrHQxKqUab6sJUhj/a+vEseA=="},"_hasShrinkwrap":false,"_npmUser":{"name":"types","email":"ts-npm-types@microsoft.com"}},"1.0.1":{"name":"@types/geojson","version":"1.0.1","dependencies":{},"peerDependencies":{},"directories":{},"dist":{"shasum":"f4783b464989c96929ef84604e95fa2ebd05ef6e","size":1288,"noattachment":false,"tarball":"https://registry.npmmirror.com/@types/geojson/-/geojson-1.0.1.tgz","integrity":"sha512-yhOL4k43uWf4ifIZShUz2NZ8btVNk/0Oon1ZwwGRHynOS1dPdShn+lA2A/qiX3r2qclO8XnZkf5e9Aq4fksYJQ=="},"_hasShrinkwrap":false,"_npmUser":{"name":"types","email":"ts-npm-types@microsoft.com"}},"1.0.0":{"name":"@types/geojson","version":"1.0.0","dependencies":{},"peerDependencies":{},"directories":{},"dist":{"shasum":"6af48a0d492c09068e97cb78e6bef940d57fb36d","size":1507,"noattachment":false,"tarball":"https://registry.npmmirror.com/@types/geojson/-/geojson-1.0.0.tgz","integrity":"sha512-VjeODoeWkxipXTF2JR9Ur51I366/qn7zLtTjOcVK+6ix1bxSQIgGfTB8BD/XprJFmqJ64o6FxyuqieogtJ/8NA=="},"_hasShrinkwrap":false,"_npmUser":{"name":"types","email":"ts-npm-types@microsoft.com"}},"0.0.32":{"name":"@types/geojson","version":"0.0.32","dependencies":{},"peerDependencies":{},"directories":{},"dist":{"shasum":"1571eeaf045337b242852885f08d9a945e1cc940","size":1427,"noattachment":false,"tarball":"https://registry.npmmirror.com/@types/geojson/-/geojson-0.0.32.tgz","integrity":"sha512-oNCBYrpksxeDtGyd4MeQOo8hMOJD4hP7lvTdu2/EP+mVtCcnb9w7jCF9SyDQS0DEA1EprfaT9rIxiX3WWyV9nA=="},"_hasShrinkwrap":false,"_npmUser":{"name":"types","email":"ts-npm-types@microsoft.com"}},"0.0.31":{"name":"@types/geojson","version":"0.0.31","dependencies":{},"directories":{},"dist":{"shasum":"ad8d4cb76f7bf13c59babc5bed77f2dd2c4175bc","size":1412,"noattachment":false,"tarball":"https://registry.npmmirror.com/@types/geojson/-/geojson-0.0.31.tgz","integrity":"sha512-8vjyb7WhrSe4XMOZpYvz4hQP+i2VR9jlmER4JLTtRamqDqcAdaXN91Cwsgk8jMbb3/PHU0EIn5G01dmuO63bMA=="},"_hasShrinkwrap":false,"_npmUser":{"name":"types","email":"ts-npm-types@microsoft.com"}},"0.0.30":{"name":"@types/geojson","version":"0.0.30","dependencies":{},"directories":{},"dist":{"shasum":"2fec45271056ed1bb2eddc394cc3057af635f488","size":1398,"noattachment":false,"tarball":"https://registry.npmmirror.com/@types/geojson/-/geojson-0.0.30.tgz","integrity":"sha512-MzkV7hPv8HsFbfHEgFvfTSFipVfNCSx9CdlC9mD6e2WhUmxJxHJsF8JdVHYgbz6qdd7NYodynRsWdy4ci8JQZA=="},"_hasShrinkwrap":false,"_npmUser":{"name":"types","email":"ts-npm-types@microsoft.com"}},"0.0.29":{"name":"@types/geojson","version":"0.0.29","dependencies":{},"directories":{},"dist":{"shasum":"03c29c420f40d43272f7ffd0bee950204c1250d1","size":1400,"noattachment":false,"tarball":"https://registry.npmmirror.com/@types/geojson/-/geojson-0.0.29.tgz","integrity":"sha512-fomjpWd/DerPpFpz3AVINErvcJCfbOYnyFbN+A6rJ8uZHVNsIAZ0TtuQ+f147TtNg5DyQwoImAyAdrDWvzAXtA=="},"_hasShrinkwrap":false,"_npmUser":{"name":"types","email":"ts-npm-types@microsoft.com"}},"0.0.28":{"name":"@types/geojson","version":"0.0.28","dependencies":{},"directories":{},"dist":{"shasum":"081f5b20516888b55bc8d88207436d94555e1f3a","size":9216,"noattachment":false,"tarball":"https://registry.npmmirror.com/@types/geojson/-/geojson-0.0.28.tgz","integrity":"sha512-oumpwbUp9kTHAJVebJ7l77oqL7uFUc0NHLWYh2q6U0/vw5xbOStc8L+9TTu64Z2FngIp/IvS1FXqUTpsp3KQvA=="},"_hasShrinkwrap":false,"_npmUser":{"name":"types","email":"ts-npm-types@microsoft.com"}},"0.0.27":{"name":"@types/geojson","version":"0.0.27","dependencies":{},"directories":{},"dist":{"shasum":"600d0c03722beb9f88548eb68182dfda3b43c8e3","size":1351,"noattachment":false,"tarball":"https://registry.npmmirror.com/@types/geojson/-/geojson-0.0.27.tgz","integrity":"sha512-P028VfkXeDmWPjlZo3M72x+w2wNkRqMNheras4hNSy13xIC0CUUEpyunKv5koBX/KydYZtFMEtKJGSZa3iMjYA=="},"_hasShrinkwrap":false,"_npmUser":{"name":"types","email":"ts-npm-types@microsoft.com"}},"0.0.26-alpha":{"name":"@types/geojson","version":"0.0.26-alpha","dependencies":{},"directories":{},"dist":{"shasum":"1b730221fe17c820c1660e6a11d0f3f759004b25","size":1355,"noattachment":false,"tarball":"https://registry.npmmirror.com/@types/geojson/-/geojson-0.0.26-alpha.tgz","integrity":"sha512-N+D8CziEZ/O3ncdtSfX7VMoU6Pq2L+GRFC2JMTt/emT9t+NSH34g5XI1HVSLm/VcKzP2QS3c1y856/HBNDEo2g=="},"_hasShrinkwrap":false,"_npmUser":{"name":"types","email":"ryan.cavanaugh@microsoft.com"}},"0.0.25-alpha":{"name":"@types/geojson","version":"0.0.25-alpha","dependencies":{},"directories":{},"dist":{"shasum":"664b1da19f37f19b86bb4bb683c8341dbfbe373d","size":1355,"noattachment":false,"tarball":"https://registry.npmmirror.com/@types/geojson/-/geojson-0.0.25-alpha.tgz","integrity":"sha512-SYzW5VrP1vsuxKbOUK2n8gGgKSHUwbBRFIR1QvGsyAzeOAVwWb7oYTvHrusV1LJNzZ/DPplwsEXBTldoSq7R2A=="},"_hasShrinkwrap":false,"_npmUser":{"name":"types","email":"ryan.cavanaugh@microsoft.com"}},"0.0.24-alpha":{"name":"@types/geojson","version":"0.0.24-alpha","dependencies":{},"directories":{},"dist":{"shasum":"bf02e7cd4f823c555d9bb2451682eac8a8331e95","size":1356,"noattachment":false,"tarball":"https://registry.npmmirror.com/@types/geojson/-/geojson-0.0.24-alpha.tgz","integrity":"sha512-UJihT17qrTZhh919qk+vxsgnqkDXu/L94KlTeUnSjsWz/TubnrdX+lUxm4HkqbPkin861+8/1QbNhJBZ5QXi1g=="},"_hasShrinkwrap":false,"_npmUser":{"name":"types","email":"ryan.cavanaugh@microsoft.com"}},"0.0.23-alpha":{"name":"@types/geojson","version":"0.0.23-alpha","dependencies":{},"directories":{},"dist":{"shasum":"bcb7a25616135e4537530dc583d53d6b0a23650d","size":1355,"noattachment":false,"tarball":"https://registry.npmmirror.com/@types/geojson/-/geojson-0.0.23-alpha.tgz","integrity":"sha512-JVjhf6nWQFKeHTxd0mVvAabE0393iFA1UaK1vksDFr8CEcJYvZYDyx5ncUBKTn7Vus9YC3IHFr2O/K0xN9uKJg=="},"_hasShrinkwrap":false,"_npmUser":{"name":"types","email":"ryan.cavanaugh@microsoft.com"}},"0.0.22-alpha":{"name":"@types/geojson","version":"0.0.22-alpha","dependencies":{},"directories":{},"dist":{"shasum":"478072d0cf5ed395bcd9f826a9b2ffa5f2671c2e","size":1353,"noattachment":false,"tarball":"https://registry.npmmirror.com/@types/geojson/-/geojson-0.0.22-alpha.tgz","integrity":"sha512-xr+8cAfN+EnUVxhSti9wy5iHgyGVPecfoJNcuqDChTmPGagq+FJ6ZVXv+36K2VfMxK6ohL0/E1KytIaUPfcN+A=="},"_hasShrinkwrap":false,"_npmUser":{"name":"types","email":"ryan.cavanaugh@microsoft.com"}},"0.0.21-alpha":{"name":"@types/geojson","version":"0.0.21-alpha","dependencies":{},"directories":{},"dist":{"shasum":"a6b0e695fa0ae4568cf8b5e31cc09a94522e0f51","size":1324,"noattachment":false,"tarball":"https://registry.npmmirror.com/@types/geojson/-/geojson-0.0.21-alpha.tgz","integrity":"sha512-vCH39Y10+3RhKxeU7wdKt4aBhaiS4wO/34aFfUPApQuyWzBUh7WoyIG61fmjNfi8h7AoWY+GcwIuS7GYO5FPEg=="},"_hasShrinkwrap":false,"_npmUser":{"name":"types","email":"ryan.cavanaugh@microsoft.com"}},"0.0.20-alpha":{"name":"@types/geojson","version":"0.0.20-alpha","dependencies":{},"directories":{},"dist":{"shasum":"1e80d443cc72d22ac854a7ff59919c868284df46","size":1322,"noattachment":false,"tarball":"https://registry.npmmirror.com/@types/geojson/-/geojson-0.0.20-alpha.tgz","integrity":"sha512-rmcoqDIMlczZvh2ef5WHv3uSs+W2OpWIQQlC+MTP2U6qEgHZDii/rQ3NZJMED3rWqEG6m1gcIh4BGFc1LHozvQ=="},"_hasShrinkwrap":false,"_npmUser":{"name":"types","email":"ryan.cavanaugh@microsoft.com"}},"0.0.15-alpha":{"name":"@types/geojson","version":"0.0.15-alpha","dependencies":{},"directories":{},"dist":{"shasum":"7e1df610295f638c6c9990bdf297f8201c8ad999","size":1331,"noattachment":false,"tarball":"https://registry.npmmirror.com/@types/geojson/-/geojson-0.0.15-alpha.tgz","integrity":"sha512-TVqEfxPVBImd1wKeZ+MYTYxTQbpPaI4iQMraAc70FhUuoaImfJnqq1iyStewnmPpb7QA7K48TR4maOXBHwla6g=="},"_hasShrinkwrap":false,"_npmUser":{"name":"types","email":"ryan.cavanaugh@microsoft.com"}},"0.0.14-alpha":{"name":"@types/geojson","version":"0.0.14-alpha","dependencies":{},"directories":{},"dist":{"shasum":"392c2d13d4803da1cd39dea8270abfc6d7b637d2","size":1322,"noattachment":false,"tarball":"https://registry.npmmirror.com/@types/geojson/-/geojson-0.0.14-alpha.tgz","integrity":"sha512-DuZ1eMm1nQnuZTomfxrTsbzJgkQy3KjstY5IoF9COz0rANYSB2YPq4+wNVDH98OxS3YOYa+lw606Wk0aF+ss5Q=="},"_hasShrinkwrap":false,"_npmUser":{"name":"types","email":"ryan.cavanaugh@microsoft.com"}},"7946.0.9":{"name":"@types/geojson","version":"7946.0.9","dependencies":{},"directories":{},"dist":{"integrity":"sha512-snVY+R7d0VfUEHdfEe/NTFnz0+Qei0kEGIV8ErryWQwDXNS7uzhVEMcUtZ+uBHXSBcJa0zBcevBE0u41acbodQ==","shasum":"dd5d4c39c989c01f49c1b05df5826ffd4ddae1e9","tarball":"https://registry.npmmirror.com/@types/geojson/-/geojson-7946.0.9.tgz","fileCount":5,"unpackedSize":8630,"signatures":[{"keyid":"SHA256:jl3bwswu80PjjokCgh0o2w5c2U4LhQAE57gj9cz1kzA","sig":"MEUCIQCrX7HRuWznmxS8proBOH6WlAzrFJj5OCDpZf11ivS/RgIgFz2rxawqzh0uJZ+WPH51ypX+Lyn7fLO177wxk9tnzdk="}],"npm-signature":"-----BEGIN PGP SIGNATURE-----\r\nVersion: OpenPGP.js v4.10.10\r\nComment: https://openpgpjs.org\r\n\r\nwsFzBAEBCAAGBQJizgvfACEJED1NWxICdlZqFiEECWMYAoorWMhJKdjhPU1b\r\nEgJ2VmroJxAAk6kQK2cnLwM5QSXBVgt+sRbgvd1NMyjRIqKL/BlZoOhI8gtG\r\nEyk67+bzaMuqDT7ZxZbk/B5vfAJ386ahdDq9Gh43OXMap1NmkPtPdsbwsjX6\r\nJ5ZKLEYlbW3iUO+oQy4/ngr8HrP/z6Tl8zL2vJ27MdsRqzpgAsakDK5fDRzo\r\nDzTPL1VBV23nY41VJZ4VQTd294Gv5ADvphEMNL3IO0BK2sWm9Uj9rv/Ak57C\r\nxHaWknJdSIOc21DLh7cIFih3pKyHLqT/5xgnFzmpKJKLUDGc80ixoTcqZnK/\r\n/rRIaklgDRbUvvbzyuasl+zCR7HNQWIidqsXGS1We6/aTPolDACEn7nMZdgm\r\nfzzJjKSqr6rVz0te3RJ7Xww7mSc8qk8h3krBx39l/SeT/HPcz3UuYTRx7qSY\r\nY/vhi4H+iaHMDg6NZf+jDI0RzDNOXDQ01brRAJWp4gwstJvnbmLix939FZgg\r\nhG2+EbYkfZQgKLqBA2jorXHrHTu1xedQcS2FxrwxjA/F1bU9tel9MS4ss8CI\r\nR2mJzQW8SS4bcTuUorfuHJnn5vqmH9g6W7/7UQoSicBaIEXoRSJkxs5vMXBd\r\nklntW1XGolLxknFpXJKhX1fcFugPHcsWiRiESC9MPlTUa/kJnHGUuj/tYsan\r\nr/HRf5xKYcWfaUPM5oVtQhfym1uOvLRabXg=\r\n=i22W\r\n-----END PGP SIGNATURE-----\r\n","size":2972},"_hasShrinkwrap":false,"_npmUser":{"name":"types","email":"ts-npm-types@microsoft.com"}},"7946.0.10":{"name":"@types/geojson","version":"7946.0.10","dependencies":{},"directories":{},"dist":{"integrity":"sha512-Nmh0K3iWQJzniTuPRcJn5hxXkfB1T1pgB89SBig5PlJQU5yocazeu4jATJlaA0GYFKWMqDdvYemoSnF2pXgLVA==","shasum":"6dfbf5ea17142f7f9a043809f1cd4c448cb68249","tarball":"https://registry.npmmirror.com/@types/geojson/-/geojson-7946.0.10.tgz","fileCount":5,"unpackedSize":8631,"signatures":[{"keyid":"SHA256:jl3bwswu80PjjokCgh0o2w5c2U4LhQAE57gj9cz1kzA","sig":"MEUCIGtdM+SfPlXF5hX0j5flAOldO1CtzdDFJcgh4vx40U6wAiEAigmPXaRTbcy8SBX/yNRSJJVm8hxoMegJqNPEtEqkD9c="}],"npm-signature":"-----BEGIN PGP SIGNATURE-----\r\nVersion: OpenPGP.js v4.10.10\r\nComment: https://openpgpjs.org\r\n\r\nwsFzBAEBCAAGBQJiz10SACEJED1NWxICdlZqFiEECWMYAoorWMhJKdjhPU1b\r\nEgJ2Vmq4LBAAnpjTXI51G7m7QM8f8gnyd+BPsOmygLzlcS2Ms35kwVQQzJR3\r\npnNzlaXVH0JXcmG7J1aQ3xmaA9TpWMv3VMJM4spZlSLJn5s6ci1Ygl8d0euK\r\nwHO+O8MUFtAer9fuLNM18hG+nn03ogK+DL2W1n9BbIVg6Qi/XDTLrCGWAGgf\r\n+nV7XzizSDlknvIwMP2qTcv9hHa9+Y3hWpaCY/XHUSKV4hQoEcDoSS6xGPws\r\nQGh4nh7ZcVlSZhpDA9jg8st2Yk4MKTsmR+up8tMLGPrwgIrYoz82d2OeSzgy\r\nBCmT5uaPephSduVlD9trHtYZsLisT25hAVLiF/sTKUTqK4w+NEubEtgvmX93\r\nHNNY/RoYjsM/ZJL+KQJwXB4j2d+ZbZ41sXbG8VvS4K0A+P29l9TLcJ9bMINr\r\nS4quObqlS+l0lVnJn+UIL1ZoR91tqf7Ka9yBk5ZJ4mOYGY7IH4XdzM5c4K69\r\n+cefTJxEfjGiFqtep0X4Vfi0R6YD+1/BZtb231AgWaxEOgppFVfBCXnYiUlS\r\n6Nrt/NGrKKBtaFAUKn4wmIz9StrmZODNcv2rWRV/25cvMycKoyq3XJEtuu5X\r\nZALgZkNSDBAiPP1nV1VZyd741kN950DS6a8iDIOFhdR5Sw1kui3ihDGfcuDd\r\n28eKbkkRoGOpS67RzmozZoasPrCEQZFBiG4=\r\n=Xv1B\r\n-----END PGP SIGNATURE-----\r\n","size":2969},"_hasShrinkwrap":false,"_npmUser":{"name":"types","email":"ts-npm-types@microsoft.com"}},"7946.0.11":{"name":"@types/geojson","version":"7946.0.11","dependencies":{},"directories":{},"dist":{"integrity":"sha512-L7A0AINMXQpVwxHJ4jxD6/XjZ4NDufaRlUJHjNIFKYUFBH1SvOW+neaqb0VTRSLW5suSrSu19ObFEFnfNcr+qg==","shasum":"012c17cb2256ad8de78560da851ab914a7b9b40e","tarball":"https://registry.npmmirror.com/@types/geojson/-/geojson-7946.0.11.tgz","fileCount":5,"unpackedSize":8631,"signatures":[{"keyid":"SHA256:jl3bwswu80PjjokCgh0o2w5c2U4LhQAE57gj9cz1kzA","sig":"MEUCIQDerNUgU92hqRAv9MqWANNksKUsOng1OhBIbKaXYFYPFAIgYpgSKQwGUS+FsCyP2EXHwaFdqeGInOxag3jY2YuiH1Y="}],"size":2984},"_hasShrinkwrap":false,"publish_time":1695230269764,"_source_registry_name":"default"},"7946.0.12":{"name":"@types/geojson","version":"7946.0.12","dependencies":{},"directories":{},"dist":{"integrity":"sha512-uK2z1ZHJyC0nQRbuovXFt4mzXDwf27vQeUWNhfKGwRcWW429GOhP8HxUHlM6TLH4bzmlv/HlEjpvJh3JfmGsAA==","shasum":"0307536218d32e6b970bccd1d148b9c4e5b6f10d","tarball":"https://registry.npmmirror.com/@types/geojson/-/geojson-7946.0.12.tgz","fileCount":5,"unpackedSize":8127,"signatures":[{"keyid":"SHA256:jl3bwswu80PjjokCgh0o2w5c2U4LhQAE57gj9cz1kzA","sig":"MEYCIQCKRPYSSJaz0tidheKR/9J5RaLjQB0GrnwkJFdzbhXWXAIhAOZQ8x3zNxU+xijXbhM+EYXJ3fTtSS/NNLILQ9FqyTv4"}],"size":2881},"_hasShrinkwrap":false,"publish_time":1697600960018,"_source_registry_name":"default"},"7946.0.13":{"name":"@types/geojson","version":"7946.0.13","dependencies":{},"directories":{},"dist":{"integrity":"sha512-bmrNrgKMOhM3WsafmbGmC+6dsF2Z308vLFsQ3a/bT8X8Sv5clVYpPars/UPq+sAaJP+5OoLAYgwbkS5QEJdLUQ==","shasum":"e6e77ea9ecf36564980a861e24e62a095988775e","tarball":"https://registry.npmmirror.com/@types/geojson/-/geojson-7946.0.13.tgz","fileCount":5,"unpackedSize":8127,"signatures":[{"keyid":"SHA256:jl3bwswu80PjjokCgh0o2w5c2U4LhQAE57gj9cz1kzA","sig":"MEYCIQCfrvryYIuZVtOsBcRmZzlSf/BGfeC7ExmaOFRj2SaYagIhAP4zv16kiNW0pugYl9t6giMdg9DB8700u27+Gd3MSabj"}],"size":2878},"_hasShrinkwrap":false,"publish_time":1699335971399,"_source_registry_name":"default"},"7946.0.14":{"name":"@types/geojson","version":"7946.0.14","dependencies":{},"directories":{},"dist":{"integrity":"sha512-WCfD5Ht3ZesJUsONdhvm84dmzWOiOzOAqOncN0++w0lBw1o8OuDNJF2McvvCef/yBqb/HYRahp1BYtODFQ8bRg==","shasum":"319b63ad6df705ee2a65a73ef042c8271e696613","tarball":"https://registry.npmmirror.com/@types/geojson/-/geojson-7946.0.14.tgz","fileCount":5,"unpackedSize":8107,"signatures":[{"keyid":"SHA256:jl3bwswu80PjjokCgh0o2w5c2U4LhQAE57gj9cz1kzA","sig":"MEYCIQDJexnW/ivDUwUdp+DpJGQbf9hpAQNtQkTs3VM5h372wQIhAJoqE9g5Conj/SvC6bdtWQT7VDcK2/vWaGmZcgbJU0QM"}],"size":2870},"_hasShrinkwrap":false,"publish_time":1706650902311,"_source_registry_name":"default"},"7946.0.15":{"name":"@types/geojson","version":"7946.0.15","dependencies":{},"peerDependencies":{},"directories":{},"dist":{"shasum":"f9d55fd5a0aa2de9dc80b1b04e437538b7298868","tarball":"https://registry.npmmirror.com/@types/geojson/-/geojson-7946.0.15.tgz","fileCount":5,"integrity":"sha512-9oSxFzDCT2Rj6DfcHF8G++jxBKS7mBqXl5xrRW+Kbvjry6Uduya2iiwqHPhVXpasAVMBYKkEPGgKhd3+/HZ6xA==","signatures":[{"sig":"MEYCIQC3lqYGpo/aoQuOoYIWXH+43MDXmELZHxMnHPpfc3lxLQIhAIYvrRw2EVA6TueJI1oPIhNirwOGrvnXa+Xt6cjrzfFj","keyid":"SHA256:jl3bwswu80PjjokCgh0o2w5c2U4LhQAE57gj9cz1kzA"}],"unpackedSize":8215,"size":2885},"_hasShrinkwrap":false,"publish_time":1733492263230,"_source_registry_name":"default"},"7946.0.16":{"name":"@types/geojson","version":"7946.0.16","dependencies":{},"peerDependencies":{},"directories":{},"dist":{"shasum":"8ebe53d69efada7044454e3305c19017d97ced2a","tarball":"https://registry.npmmirror.com/@types/geojson/-/geojson-7946.0.16.tgz","fileCount":5,"integrity":"sha512-6C8nqWur3j98U6+lXDfTUWIfgvZU+EumvpHKcYjujKH7woYyLj2sUmff0tRhrqM7BohUw7Pz3ZB1jj2gW9Fvmg==","signatures":[{"sig":"MEQCIBqch7O8MI5jLeLlLx+PUWRJTnDM5b2h4HPkoMLywEHoAiBjloqS+2e4AJ/9+xrWLp1jbN0N2WduWMDvHYIZzO67sQ==","keyid":"SHA256:DhQ8wR5APBvFHLF/+Tc+AYvPOdTpcIDqOhxsBHRwC7U"}],"unpackedSize":9514,"size":3385},"_hasShrinkwrap":false,"publish_time":1737657421847,"_source_registry_name":"default"}},"_source_registry_name":"default","cachedAt":1775979514173}